slack_error_notifier.py
slack_error_notifier-1.0.4.dist-info/METADATA
slack_error_notifier-1.0.4.dist-info/WHEEL
slack_error_notifier-1.0.4.dist-info/top_level.txt
slack_error_notifier-1.0.4.dist-info/RECORD
